Workbook

Sheet Assumptions
A1: ASSUMPTIONS – INPUT PARAMETERS (APRIL 2026)
A3: Parameter | B3: 2026 Value
A4: Total homes target (2030) | B4: 303000
A5: 2025 completions (actual) | B5: 36248
A6: 2026 completions (forecast) | B6: 36500
A7: 2027 completions (forecast) | B7: 38000
A8: 2028 completions (forecast) | B8: 39500
A9: 2029 completions (forecast) | B9: 41000
A10: Modular share - 2026 | B10: 0.08
A11: Modular share - 2027 | B11: 0.1
A12: Modular share - 2028 | B12: 0.12
A13: Modular share - 2029 | B13: 0.15
A14: Cost: Standard house (€) | B14: 397000
A15: Cost: Modular house (€) | B15: 320000
... A29: GVA multiplier (construction) | B29: 0.38
A30: Modular policy status | B30: Proposed – pending Cabinet approval
A31: Garden unit exemption cap (sq m) | B31: 25
A32: Garden unit max size (sq m) | B32: 45
A33: Indirect employment multiplier (MMC) | B33: 1.5
A34: Labor headroom max | B34: 185000
A35: Current employment (Q4 2025) | B35: 175000
A36: VAT / Corp tax sunset date | B36: 31/12/2030

Sheet Housing_Delivery
A1: HOUSING DELIVERY – UNITS BY TYPE (2025-2029)
A2: Year | B2: Total Completions | C2: Modular Share | D2: Modular Houses | E2: Traditional Houses | F2: Modular Apartments | G2: Traditional Apartments
A3: 2025 | B3: =Assumptions!$B$5 -> 36248 | C3: 0.05 | D3: =B3*C3*0.6 -> 1087.44 | E3: =B3*(1-C3)*0.6 -> 20661.36 | F3: =B3*C3*0.4 -> 724.96 | G3: =B3*(1-C3)*0.4 -> 13774.24
A4: 2026 | B4: =Assumptions!$B$6 -> 36500 | C4: =Assumptions!$B$10 -> 0.08 | D4: =B4*C4*0.6 -> 1752 | E4: =B4*(1-C4)*0.6 -> 20148 | F4: =B4*C4*0.4 -> 1168 | G4: =B4*(1-C4)*0.4 -> 13432
A5: 2027 | B5: =Assumptions!$B$7 -> 38000 | C5: =Assumptions!$B$11 -> 0.1 | D5: =B5*C5*0.6 -> 2280 | E5: =B5*(1-C5)*0.6 -> 20520 | F5: =B5*C5*0.4 -> 1520 | G5: =B5*(1-C5)*0.4 -> 13680
A6: 2028 | B6: =Assumptions!$B$8 -> 39500 | C6: =Assumptions!$B$12 -> 0.12 | D6: =B6*C6*0.6 -> 2844 | E6: =B6*(1-C6)*0.6 -> 20856 | F6: =B6*C6*0.4 -> 1896 | G6: =B6*(1-C6)*0.4 -> 13904
A7: 2029 | B7: =Assumptions!$B$9 -> 41000 | C7: =Assumptions!$B$13 -> 0.15 | D7: =B7*C7*0.6 -> 3690 | E7: =B7*(1-C7)*0.6 -> 20910 | F7: =B7*C7*0.4 -> 2460 | G7: =B7*(1-C7)*0.4 -> 13940
A8: TOTALS | B8: =SUM(B3:B7) -> 191248 | C8: =AVERAGE(C3:C7) -> 0.1 | D8: =SUM(D3:D7) -> 11653.44 | E8: =SUM(E3:E7) -> 103095.36 | F8: =SUM(F3:F7) -> 7768.96 | G8: =SUM(G3:G7) -> 68730.24

Sheet Economic_Impact
A1: ECONOMIC IMPACT – JOBS, GVA & TAX REVENU
A2: Year | B2: Investment (€m) | C2: Direct Jobs | D2: GVA (€m) | E2: Income Tax (€m) | F2: VAT Houses (€m) | G2: VAT Apts (€m) | H2: Corp Tax (€m) | I2: Indirect Jobs
A3: 2025 | B3: =(Housing_Delivery!D3*Assumptions!$B$14 + Housing_Delivery!E3*Assumptions!$B$14 + Housing_Delivery!F3*Assumptions!$B$17 + Housing_Delivery!G3*Assumptions!$B$16)/1000000 -> 13313.89 | C3: =B3*1000000/Assumptions!$B$23*0.1 -> 22758.787 | D3: =C3*Assumptions!$B$23/1000000 -> 1331.389 | E3: =C3*Assumptions!$B$23*Assumptions!$B$24/1000000 -> 359.47504 | F3: =(Housing_Delivery!D3*Assumptions!$B$14 + Housing_Delivery!E3*Assumptions!$B$14)*Assumptions!$B$19/1000000 -> 1165.6269 | G3: =(Housing_Delivery!F3*Assumptions!$B$17 + Housing_Delivery!G3*Assumptions!$B$16)*Assumptions!$B$20/1000000 -> 421.16551 | H3: =(D3*Assumptions!$B$21)*0.5 -> 99.854178 | I3: =C3*Assumptions!$B$33 -> 34138.181
A4: 2026 | B4: =(Housing_Delivery!D4*Assumptions!$B$14 + Housing_Delivery!E4*Assumptions!$B$14 + Housing_Delivery!F4*Assumptions!$B$17 + Housing_Delivery!G4*Assumptions!$B$16)/1000000 -> 13386.74 | C4: =B4*1000000/Assumptions!$B$23*0.1 -> 22883.316 | D4: =C4*Assumptions!$B$23/1000000 -> 1338.674 | E4: =C4*Assumptions!$B$23*Assumptions!$B$24/1000000 -> 361.44198 | F4: =(Housing_Delivery!D4*Assumptions!$B$14 + Housing_Delivery!E4*Assumptions!$B$14)*Assumptions!$B$19/1000000 -> 1173.7305 | G4: =(Housing_Delivery!F4*Assumptions!$B$17 + Housing_Delivery!G4*Assumptions!$B$16)*Assumptions!$B$20/1000000 -> 422.3196 | H4: =(D4*Assumptions!$B$21)*0.5 -> 100.40055 | I4: =C4*Assumptions!$B$33 -> 34324.974
A5: 2027 | B5: =(Housing_Delivery!D5*Assumptions!$B$14 + Housing_Delivery!E5*Assumptions!$B$14 + Housing_Delivery!F5*Assumptions!$B$17 + Housing_Delivery!G5*Assumptions!$B$16)/1000000 -> 13923.2 | C5: =B5*1000000/Assumptions!$B$23*0.1 -> 23800.342 | D5: =C5*Assumptions!$B$23/1000000 -> 1392.32 | E5: =C5*Assumptions!$B$23*Assumptions!$B$24/1000000 -> 375.9264 | F5: =(Housing_Delivery!D5*Assumptions!$B$14 + Housing_Delivery!E5*Assumptions!$B$14)*Assumptions!$B$19/1000000 -> 1221.966 | G5: =(Housing_Delivery!F5*Assumptions!$B$17 + Housing_Delivery!G5*Assumptions!$B$16)*Assumptions!$B$20/1000000 -> 438.444 | H5: =(D5*Assumptions!$B$21)*0.5 -> 104.424 | I5: =C5*Assumptions!$B$33 -> 35700.513
A6: 2028 | B6: =(Housing_Delivery!D6*Assumptions!$B$14 + Housing_Delivery!E6*Assumptions!$B$14 + Housing_Delivery!F6*Assumptions!$B$17 + Housing_Delivery!G6*Assumptions!$B$16)/1000000 -> 14458.58 | C6: =B6*1000000/Assumptions!$B$23*0.1 -> 24715.521 | D6: =C6*Assumptions!$B$23/1000000 -> 1445.858 | E6: =C6*Assumptions!$B$23*Assumptions!$B$24/1000000 -> 390.38166 | F6: =(Housing_Delivery!D6*Assumptions!$B$14 + Housing_Delivery!E6*Assumptions!$B$14)*Assumptions!$B$19/1000000 -> 1270.2015 | G6: =(Housing_Delivery!F6*Assumptions!$B$17 + Housing_Delivery!G6*Assumptions!$B$16)*Assumptions!$B$20/1000000 -> 454.4712 | H6: =(D6*Assumptions!$B$21)*0.5 -> 108.43935 | I6: =C6*Assumptions!$B$33 -> 37073.282
A7: 2029 | B7: =(Housing_Delivery!D7*Assumptions!$B$14 + Housing_Delivery!E7*Assumptions!$B$14 + Housing_Delivery!F7*Assumptions!$B$17 + Housing_Delivery!G7*Assumptions!$B$16)/1000000 -> 14985.5 | C7: =B7*1000000/Assumptions!$B$23*0.1 -> 25616.239 | D7: =C7*Assumptions!$B$23/1000000 -> 1498.55 | E7: =C7*Assumptions!$B$23*Assumptions!$B$24/1000000 -> 404.6085 | F7: =(Housing_Delivery!D7*Assumptions!$B$14 + Housing_Delivery!E7*Assumptions!$B$14)*Assumptions!$B$19/1000000 -> 1318.437 | G7: =(Housing_Delivery!F7*Assumptions!$B$17 + Housing_Delivery!G7*Assumptions!$B$16)*Assumptions!$B$20/1000000 -> 469.737 | H7: =(D7*Assumptions!$B$21)*0.5 -> 112.39125 | I7: =C7*Assumptions!$B$33 -> 38424.359
A8: TOTALS | B8: =SUM(B3:B7) -> 70067.91 | C8: =SUM(C3:C7) -> 119774.21 | D8: =SUM(D3:D7) -> 7006.791 | E8: =SUM(E3:E7) -> 1891.8336 | F8: =SUM(F3:F7) -> 6149.9619 | G8: =SUM(G3:G7) -> 2206.1373 | H8: =SUM(H3:H7) -> 525.50933 | I8: =SUM(I3:I7) -> 179661.31

Sheet Rent_Impact
A1: RENT IMPACT – GARDEN MODULAR UNITS
A2: Scenario | B2: Annual Rent (€) | C2: Taxable Income | D2: After-Tax Return (€) | E2: Tenant Status
A3: Included in rent-a-room (≤45 sq m, 25 sq m garden) | B3: 14000 | C3: 0 | D3: 14000 | E3: Licensee
A4: Excluded (standard rental – >45 sq m) | B4: 20000 | C4: 20000 | D4: =B4*(1-Assumptions!$B$24-Assumptions!$B$25-Assumptions!$B$26) -> 13200 | E4: Tenant
A5: Excluded (market rate) | B5: 25000 | C5: 25000 | D5: =B5*(1-Assumptions!$B$24-Assumptions!$B$25-Assumptions!$B$26) -> 16500 | E5: Tenant

Sheet NPV_Calculation
A1: NET PRESENT VALUE – DISCOUNTED CASHFLOW (4%)
A2: Year | B2: Net Benefit (€m) | C2: Discount Factor | D2: PV (€m) | E2: Cumulative PV (€m)
A3: 2025 | B3: =Economic_Impact!B3+Economic_Impact!E3+Economic_Impact!F3+Economic_Impact!G3+Economic_Impact!H3 -> 15360.012 | C3: =1/(1+Assumptions!$B$28)^(A3-2025) -> 1 | D3: =B3*C3 -> 15360.012 | E3: =D3 -> 15360.012
A4: 2026 | B4: =Economic_Impact!B4+Economic_Impact!E4+Economic_Impact!F4+Economic_Impact!G4+Economic_Impact!H4 -> 15444.633 | C4: =1/(1+Assumptions!$B$28)^(A4-2025) -> 0.96153846 | D4: =B4*C4 -> 14850.608 | E4: =E3+D4 -> 30210.62
A5: 2027 | B5: =Economic_Impact!B5+Economic_Impact!E5+Economic_Impact!F5+Economic_Impact!G5+Economic_Impact!H5 -> 16063.96 | C5: =1/(1+Assumptions!$B$28)^(A5-2025) -> 0.92455621 | D5: =B5*C5 -> 14852.034 | E5: =E4+D5 -> 45062.655
A6: 2028 | B6: =Economic_Impact!B6+Economic_Impact!E6+Economic_Impact!F6+Economic_Impact!G6+Economic_Impact!H6 -> 16682.074 | C6: =1/(1+Assumptions!$B$28)^(A6-2025) -> 0.88899636 | D6: =B6*C6 -> 14830.303 | E6: =E5+D6 -> 59892.958
A7: 2029 | B7: =Economic_Impact!B7+Economic_Impact!E7+Economic_Impact!F7+Economic_Impact!G7+Economic_Impact!H7 -> 17290.674 | C7: =1/(1+Assumptions!$B$28)^(A7-2025) -> 0.85480419 | D7: =B7*C7 -> 14780.14 | E7: =E6+D7 -> 74673.098
A8: NPV (€bn) | E8: =E7/1000 -> 74.673098

Sheet Summary
A1: SUMMARY – KEY ECONOMIC METRICS | E1: Jobs Supported by Year (Person-Years) | I1: Prepared by Mohamed Abdurrahman Mohamed
A2: MODULAR HOUSING – ECONOMIC IMPACT ASSESSMENT (2026-2029) | E2: Year | F2: Direct Jobs | G2: Indirect Jobs | I2: v1.0 – April 2026 | Economic Impact Assessment
A3: KEY METRICS | B3: VALUE | C3: UNIT | E3: 2025 | F3: =Economic_Impact!C3 -> 22758.787 | G3: =Economic_Impact!I3 -> 34138.181
A4: Total Homes Delivered | B4: =Housing_Delivery!B8 -> 191248 | C4: units | E4: 2026 | F4: =Economic_Impact!C4 -> 22883.316 | G4: =Economic_Impact!I4 -> 34324.974
A5: Total Investment | B5: =Economic_Impact!B8/1000 -> 70.06791 | C5: € billion | E5: 2027 | F5: =Economic_Impact!C5 -> 23800.342 | G5: =Economic_Impact!I5 -> 35700.513
A6: Total Gross Value Added (GVA) | B6: =Economic_Impact!D8/1000 -> 7.006791 | C6: € billion | E6: 2028 | F6: =Economic_Impact!C6 -> 24715.521 | G6: =Economic_Impact!I6 -> 37073.282
A7: Total Direct Jobs | B7: =Economic_Impact!C8 -> 119774.21 | C7: person-years | E7: 2029 | F7: =Economic_Impact!C7 -> 25616.239 | G7: =Economic_Impact!I7 -> 38424.359
A8: Total Indirect Jobs | B8: =Economic_Impact!I8 -> 179661.31 | C8: person-years
A9: Total Jobs Supported | B9: =Economic_Impact!C8+Economic_Impact!I8 -> 299435.51 | C9: person-years
A10: EXCHEQUER RETURNS
A11: Income Tax | B11: =Economic_Impact!E8/1000 -> 1.8918336 | C11: € billion
A12: VAT (Houses) | B12: =Economic_Impact!F8/1000 -> 6.1499619 | C12: € billion
A13: VAT (Apartments) | B13: =Economic_Impact!G8/1000 -> 2.2061373 | C13: € billion
A14: Corporation Tax | B14: =Economic_Impact!H8/1000 -> 0.52550933 | C14: € billion
A15: Total Exchequer Return | B15: =(Economic_Impact!E8+Economic_Impact!F8+Economic_Impact!G8+Economic_Impact!H8)/1000 -> 10.773442 | C15: € billion
A16: NPV (5-Year) | B16: =NPV_Calculation!E8 -> 74.673098 | C16: € billion
A17: Discount Rate Applied | B17: =Assumptions!$B$28 -> 0.04 | C17: %
A19: Note: This analysis assumes completions increase from 36,000 in 2026 to 41,000 in 2029, consistent with ESRI structural demand estimates (~44,000/year). Actual CSO completions in 2025 were 30,330 units. The model illustrates the economic impact of achieving policy targets under modular adoption.
